nadl-1.12.7.dist-info/METADATA
nadl-1.12.7.dist-info/WHEEL
nadl-1.12.7.dist-info/entry_points.txt
nadl/.DS_Store
nadl/__init__.py
nadl/blocks.py
nadl/data.py
nadl/data_v1.py
nadl/images.py
nadl/keys.py
nadl/loops.py
nadl/math.py
nadl/metrics.py
nadl/nets.py
nadl/preprocessing.py
nadl/py.typed
nadl/resnet.py
nadl/states.py
nadl/surgery.py
nadl/transformers.py
nadl/typings.py
nadl/utils.py
nadl-1.12.7.dist-info/RECORD
