Metadata-Version: 2.1
Name: nadl
Version: 1.12.7
Summary: Nasy's Deep Learning Toolkit
Author-Email: Nasy <nasyxx+python@gmail.com>, Nasy <nasyxx+dl@gmail.com>, Nasy <nasyxx+git@gmail.com>
License: GPLv3
Requires-Python: >=3.12
Requires-Dist: jax>=0.4.31
Requires-Dist: numpy>=1.26.4
Requires-Dist: rich>=13.8.1
Requires-Dist: jaxtyping>=0.2.34
Requires-Dist: optax>=0.2.3
Requires-Dist: equinox>=0.11.7
Requires-Dist: beartype>=0.18.5
Requires-Dist: scikit-image>=0.24.0
Requires-Dist: orbax-checkpoint>=0.6.4
Requires-Dist: scikit-learn>=1.5.2
Requires-Dist: einops>=0.8.0
Requires-Dist: haliax>=1.3
Provides-Extra: doc
Requires-Dist: mkdocs-material>=9.5.35; extra == "doc"
Requires-Dist: mkdocs>=1.6.1; extra == "doc"
Requires-Dist: mike>=2.1.3; extra == "doc"
Requires-Dist: mkdocstrings[python]>=0.26.1; extra == "doc"
Provides-Extra: mac
Requires-Dist: torch>=2.4.1; sys_platform == "darwin" and extra == "mac"
Requires-Dist: tensorflow>=2.17.0; sys_platform == "darwin" and extra == "mac"
Requires-Dist: tensordict>=0.5.0; sys_platform == "darwin" and extra == "mac"
